{
  "uai": "0593239A",
  "type_etablissement_app": "college",
  "type_label": "Collège",
  "nom": "COLLEGE BORIS VIAN",
  "adresse": "2 rue Romain Rolland",
  "code_postal": "59170",
  "commune": "CROIX",
  "departement": "NORD",
  "secteur": "PU",
  "fiche_onisep": "https://www.onisep.fr/http/redirection/etablissement/slug/ENS.3690",
  "latitude": 50.68,
  "longitude": 3.15,
  "classement_2024": {
    "eligible": true,
    "raison_exclusion": null,
    "rang": 280,
    "score": 9.0,
    "nb_classes": 395,
    "rang_2023": 287,
    "evolution": 7,
    "indicateur_cle_variation": "- va_note_ecrit"
  },
  "indicateur_cle": {
    "nom": "Valeur ajoutée réussite",
    "nom_court": "réussite",
    "valeur": 84.0,
    "va": 1.0,
    "type": "positif"
  },
  "indicateurs_2024": {
    "taux_reu_brut": 84.0,
    "va_reu": 1.0,
    "note_ecrit_brute": 10.1,
    "va_note_ecrit": -0.1,
    "taux_acces_6e_3e": 84.0,
    "nb_candidats": 129
  },
  "indicateurs_2023": {
    "taux_reu_brut": 83.0,
    "va_reu": -3.0,
    "note_ecrit_brute": 10.7,
    "va_note_ecrit": 0.4,
    "taux_acces_6e_3e": 88.0,
    "nb_candidats": 121
  },
  "ips": {
    "valeur": 96.0,
    "ecart_type": 37.8,
    "percentile": 54,
    "quintile": 3,
    "bucket": "moyen",
    "ref_national": 106.1,
    "ref_departemental": 101.7,
    "peer_group": "college_NORD_Q3"
  },
  "ips_academie": {
    "valeur": 96.0,
    "moyenne_academie": 96.9,
    "ecart": -0.9,
    "percentile": 54,
    "quintile": 3,
    "position": "dans la moyenne"
  },
  "labels_editoriaux": {
    "dynamique": "stable",
    "contexte_social": "dans la moyenne",
    "lecture_performance": "performance attendue",
    "profil_histoire": "trajectoire stable"
  },
  "contexte": {
    "education_prioritaire": false
  },
  "narration": {
    "rang_texte": "280e sur 395",
    "evolution_texte": "en légère progression de 7 places",
    "indicateur_cle_texte": "Un indicateur ressort particulièrement : réussite, avec une valeur ajoutée de +1 points.",
    "contexte_ips": "Le profil social de l’établissement se situe dans la moyenne académique.",
    "phrase_courte": "En 2024, ce collège se maintient à la 280e sur 395.",
    "phrase_longue": "En 2024, ce collège se classe 280e sur 395. Un indicateur ressort particulièrement : réussite, avec une valeur ajoutée de +1 points. Le profil social de l’établissement se situe dans la moyenne académique."
  },
  "series": [
    {
      "uai": "0593239A",
      "type_etablissement_app": "college",
      "annee": 2022,
      "rang": 320,
      "score": 9.33,
      "eligible": true,
      "raison_exclusion": null,
      "nb_candidats": 122,
      "taux_reu": 85.0,
      "va_reu": -3.0,
      "note_ecrit": 9.4,
      "va_note_ecrit": -0.4,
      "taux_acces": 88.0,
      "va_acces": null,
      "taux_men": null,
      "va_men": null
    },
    {
      "uai": "0593239A",
      "type_etablissement_app": "college",
      "annee": 2023,
      "rang": 287,
      "score": 10.43,
      "eligible": true,
      "raison_exclusion": null,
      "nb_candidats": 121,
      "taux_reu": 83.0,
      "va_reu": -3.0,
      "note_ecrit": 10.7,
      "va_note_ecrit": 0.4,
      "taux_acces": 88.0,
      "va_acces": null,
      "taux_men": null,
      "va_men": null
    },
    {
      "uai": "0593239A",
      "type_etablissement_app": "college",
      "annee": 2024,
      "rang": 280,
      "score": 9.0,
      "eligible": true,
      "raison_exclusion": null,
      "nb_candidats": 129,
      "taux_reu": 84.0,
      "va_reu": 1.0,
      "note_ecrit": 10.1,
      "va_note_ecrit": -0.1,
      "taux_acces": 84.0,
      "va_acces": null,
      "taux_men": null,
      "va_men": null
    }
  ]
}