{
  "uai": "0623759Z",
  "type_etablissement_app": "college",
  "type_label": "Collège",
  "nom": "COLLEGE LES ARGOUSIERS",
  "adresse": "341 route du Pont d'Oye",
  "code_postal": "62215",
  "commune": "OYE PLAGE",
  "departement": "PAS-DE-CALAIS",
  "secteur": "PU",
  "fiche_onisep": "https://www.onisep.fr/http/redirection/etablissement/slug/ENS.4673",
  "latitude": 50.98,
  "longitude": 2.04,
  "classement_2024": {
    "eligible": true,
    "raison_exclusion": null,
    "rang": 275,
    "score": 9.12,
    "nb_classes": 395,
    "rang_2023": 296,
    "evolution": 21,
    "indicateur_cle_variation": "- va_reu"
  },
  "indicateur_cle": {
    "nom": "Valeur ajoutée réussite",
    "nom_court": "réussite",
    "valeur": 82.0,
    "va": -8.0,
    "type": "negatif"
  },
  "indicateurs_2024": {
    "taux_reu_brut": 82.0,
    "va_reu": -8.0,
    "note_ecrit_brute": 10.4,
    "va_note_ecrit": -0.3,
    "taux_acces_6e_3e": 95.0,
    "nb_candidats": 92
  },
  "indicateurs_2023": {
    "taux_reu_brut": 88.0,
    "va_reu": -3.0,
    "note_ecrit_brute": 10.5,
    "va_note_ecrit": -0.5,
    "taux_acces_6e_3e": 97.0,
    "nb_candidats": 101
  },
  "ips": {
    "valeur": 97.4,
    "ecart_type": 30.2,
    "percentile": 58,
    "quintile": 3,
    "bucket": "moyen",
    "ref_national": 106.1,
    "ref_departemental": 95.5,
    "peer_group": "college_PAS-DE-CALAIS_Q3"
  },
  "ips_academie": {
    "valeur": 97.4,
    "moyenne_academie": 96.9,
    "ecart": 0.5,
    "percentile": 58,
    "quintile": 3,
    "position": "dans la moyenne"
  },
  "labels_editoriaux": {
    "dynamique": "hausse",
    "contexte_social": "dans la moyenne",
    "lecture_performance": "performance attendue",
    "profil_histoire": "bonne dynamique"
  },
  "contexte": {
    "education_prioritaire": false
  },
  "narration": {
    "rang_texte": "275e sur 395",
    "evolution_texte": "en hausse de 21 places",
    "indicateur_cle_texte": "Point de vigilance principal : réussite, avec une valeur ajoutée de −8 points.",
    "contexte_ips": "Le profil social de l’établissement se situe dans la moyenne académique.",
    "phrase_courte": "Ce collège poursuit sa progression en 2024 et atteint la 275e sur 395.",
    "phrase_longue": "En 2024, ce collège progresse de 21 places et se classe 275e sur 395. Point de vigilance principal : réussite, avec une valeur ajoutée de −8 points. Le profil social de l’établissement se situe dans la moyenne académique."
  },
  "series": [
    {
      "uai": "0623759Z",
      "type_etablissement_app": "college",
      "annee": 2022,
      "rang": 155,
      "score": 11.9,
      "eligible": true,
      "raison_exclusion": null,
      "nb_candidats": 115,
      "taux_reu": 93.0,
      "va_reu": 3.0,
      "note_ecrit": 10.2,
      "va_note_ecrit": -0.1,
      "taux_acces": 95.0,
      "va_acces": null,
      "taux_men": null,
      "va_men": null
    },
    {
      "uai": "0623759Z",
      "type_etablissement_app": "college",
      "annee": 2023,
      "rang": 296,
      "score": 10.29,
      "eligible": true,
      "raison_exclusion": null,
      "nb_candidats": 101,
      "taux_reu": 88.0,
      "va_reu": -3.0,
      "note_ecrit": 10.5,
      "va_note_ecrit": -0.5,
      "taux_acces": 97.0,
      "va_acces": null,
      "taux_men": null,
      "va_men": null
    },
    {
      "uai": "0623759Z",
      "type_etablissement_app": "college",
      "annee": 2024,
      "rang": 275,
      "score": 9.12,
      "eligible": true,
      "raison_exclusion": null,
      "nb_candidats": 92,
      "taux_reu": 82.0,
      "va_reu": -8.0,
      "note_ecrit": 10.4,
      "va_note_ecrit": -0.3,
      "taux_acces": 95.0,
      "va_acces": null,
      "taux_men": null,
      "va_men": null
    }
  ]
}